flowbyte/__init__.py
flowbyte/adls.py
flowbyte/dataframe.py
flowbyte/env.py
flowbyte/log.py
flowbyte/pbi.py
flowbyte/sql.py
flowbyte/streamlit.py
flowbyte/telemetry.py
flowbyte-0.5.3.dist-info/licenses/LICENSE
flowbyte-0.5.3.dist-info/METADATA
flowbyte-0.5.3.dist-info/WHEEL
flowbyte-0.5.3.dist-info/top_level.txt
flowbyte-0.5.3.dist-info/RECORD
