Metadata-Version: 2.4
Name: flowbyte
Version: 0.5.3
Summary: ETL tool for data processing
Author-email: Kevork Keheian <flowbyte@optiret.com>
Project-URL: Homepage, https://github.com/flowbytedev/flowbyte
Project-URL: Issues, https://github.com/flowbytedev/flowbyte/issues
Classifier: Programming Language :: Python :: 3
Classifier: License :: OSI Approved :: MIT License
Classifier: Operating System :: OS Independent
Requires-Python: >=3.9
License-File: LICENSE
Requires-Dist: pandas
Requires-Dist: msal
Requires-Dist: pydantic
Requires-Dist: pyodbc
Requires-Dist: sqlalchemy
Requires-Dist: numpy
Requires-Dist: pyarrow
Requires-Dist: logfire
Requires-Dist: logfire[sqlalchemy]
Requires-Dist: logfire[system-metrics]
Requires-Dist: ipython
Requires-Dist: adlfs
Requires-Dist: python-dotenv
Requires-Dist: Authlib
Requires-Dist: streamlit
Requires-Dist: duckdb
Dynamic: license-file
